UNIOA/InitOpt_Delta_z.py
UNIOA/Init_Delta_X.py
UNIOA/Init_Delta_Y.py
UNIOA/Init_X.py
UNIOA/LevyFlight.py
UNIOA/NatureOpt.py
UNIOA/Opt_Delta_X.py
UNIOA/Opt_Delta_Y.py
UNIOA/Opt_X.py
UNIOA/Selection.py
UNIOA/__init__.py
UNIOA/comparison.py
UNIOA/optimizer_running.py
UNIOA/algs/__init__.py
UNIOA/algs/myBA.py
UNIOA/algs/myBOA.py
UNIOA/algs/myCSA.py
UNIOA/algs/myGOA.py
UNIOA/algs/myMBO.py
UNIOA/algs/myMFO.py
UNIOA/algs/myPSO.py
UNIOA/algs/unioaBA.py
UNIOA/algs/unioaBOA.py
UNIOA/algs/unioaCSA.py
UNIOA/algs/unioaGOA.py
UNIOA/algs/unioaMBO.py
UNIOA/algs/unioaMFO.py
UNIOA/algs/unioaPSO.py
UNIOA-1.0.3.dist-info/LICENSE.txt
UNIOA-1.0.3.dist-info/METADATA
UNIOA-1.0.3.dist-info/WHEEL
UNIOA-1.0.3.dist-info/top_level.txt
UNIOA-1.0.3.dist-info/RECORD
