Metadata-Version: 2.1
Name: UNIOA
Version: 1.0.3
Summary: AutoNIOA
Home-page: https://github.com/Huilin-Li/UNIOA.git
Author: Huilin
Author-email: lihuilin023@gmail.com
License: MIT
Platform: UNKNOWN
License-File: LICENSE.txt
